<study>
  <experiment_count>3</experiment_count>
  <completed_at>2021-12-08 11:36:54.417722</completed_at>
  <check>
    <message src="algos\biasedmf\rmse\LibRec-Auto_log20211208_113639.log">ERROR:root: Script failure: C:\Python38\lib\site-packages\librec_auto\core\cmd\post\slack_post.py: Post processing script at C:\Python38\lib\site-packages\librec_auto\core\cmd\post\slack_post.py failed.</message>
    <message src="algos\biasedmf\rmse\LibRec-Auto_log20211208_113639.log">Traceback (most recent call last):</message>
    <message src="algos\biasedmf\rmse\LibRec-Auto_log20211208_113639.log"/>
    <message src="algos\biasedmf\rmse\LibRec-Auto_log20211208_113639.log">  File "C:/Python38/lib/site-packages/librec_auto/core/cmd/post/slack_post.py", line 1, in &lt;module&gt;</message>
    <message src="algos\biasedmf\rmse\LibRec-Auto_log20211208_113639.log"/>
    <message src="algos\biasedmf\rmse\LibRec-Auto_log20211208_113639.log">    from slack import WebClient</message>
    <message src="algos\biasedmf\rmse\LibRec-Auto_log20211208_113639.log"/>
    <message src="algos\biasedmf\rmse\LibRec-Auto_log20211208_113639.log">ImportError: cannot import name 'WebClient' from 'slack' (C:\Python38\lib\site-packages\slack\__init__.py)</message>
    <message src="algos\biasedmf\rmse\LibRec-Auto_log20211208_113639.log"/>
    <message src="algos\biasedmf\rmse\LibRec-Auto_log20211208_113639.log"/>
  </check>
  <experiments>
    <experiment count="0">
      <!--DO NOT EDIT. File automatically generated by librec-auto-->
      <meta>
        <param>
          <name>learn-rate</name>
          <value>0.1</value>
        </param>
      </meta>
      <results>
        <folds>
          <cv id="1">
            <metric name="RMSEEvaluator">0.06444578444375351</metric>
          </cv>
          <cv id="2">
            <metric name="RMSEEvaluator">0.06446503935851676</metric>
          </cv>
          <cv id="3">
            <metric name="RMSEEvaluator">0.06447504099505443</metric>
          </cv>
          <cv id="4">
            <metric name="RMSEEvaluator">0.06448086932038793</metric>
          </cv>
          <cv id="5">
            <metric name="RMSEEvaluator">0.06444245444718787</metric>
          </cv>
        </folds>
        <averages>
          <metric name="RMSEEvaluator">0.0644618377129801</metric>
        </averages>
      </results>
    </experiment>
    <experiment count="1">
      <!--DO NOT EDIT. File automatically generated by librec-auto-->
      <meta>
        <param>
          <name>learn-rate</name>
          <value>0.01</value>
        </param>
      </meta>
      <results>
        <folds>
          <cv id="1">
            <metric name="RMSEEvaluator">0.0643930627067881</metric>
          </cv>
          <cv id="2">
            <metric name="RMSEEvaluator">0.064411007331827</metric>
          </cv>
          <cv id="3">
            <metric name="RMSEEvaluator">0.06442179429958952</metric>
          </cv>
          <cv id="4">
            <metric name="RMSEEvaluator">0.0644261798316135</metric>
          </cv>
          <cv id="5">
            <metric name="RMSEEvaluator">0.06438664498381094</metric>
          </cv>
        </folds>
        <averages>
          <metric name="RMSEEvaluator">0.06440773783072581</metric>
        </averages>
      </results>
    </experiment>
    <experiment count="2">
      <!--DO NOT EDIT. File automatically generated by librec-auto-->
      <meta>
        <param>
          <name>learn-rate</name>
          <value>0.001</value>
        </param>
      </meta>
      <results>
        <folds>
          <cv id="1">
            <metric name="RMSEEvaluator">0.06241601002124376</metric>
          </cv>
          <cv id="2">
            <metric name="RMSEEvaluator">0.062427717757796354</metric>
          </cv>
          <cv id="3">
            <metric name="RMSEEvaluator">0.06245387361847038</metric>
          </cv>
          <cv id="4">
            <metric name="RMSEEvaluator">0.06245924593897214</metric>
          </cv>
          <cv id="5">
            <metric name="RMSEEvaluator">0.06240531845351145</metric>
          </cv>
        </folds>
        <averages>
          <metric name="RMSEEvaluator">0.062432433157998825</metric>
        </averages>
      </results>
    </experiment>
  </experiments>
  <config>
    <random-seed>202001</random-seed>
    <!-- This is the configuration used to run the study. -->
    <thread-count>1</thread-count>
    <library src="system">default-algorithms.xml</library>
    <!-- DATA SECTION -->
    <data>
      <data-dir>../data</data-dir>
      <format>UIR</format>
      <data-file format="text">ratings.csv</data-file>
    </data>
    <!-- SPLITTER SECTION -->
    <splitter>
      <model count="5">kcv</model>
      <dim>userfixed</dim>
      <ratio>0.8</ratio>
      <save>true</save>
    </splitter>
    <!-- ALGORITHM SECTION -->
    <alg name="alg:biasedmf">
      <class>biasedmf</class>
      <learn-rate>
        <value>0.1</value>
        <value>0.01</value>
        <value>0.001</value>
      </learn-rate>
      <learn-rate-max>0.01</learn-rate-max>
      <learn-rate-decay>1.0</learn-rate-decay>
      <bold-driver>false</bold-driver>
      <iterator-max>10</iterator-max>
      <user-reg>0.01</user-reg>
      <item-reg>0.01</item-reg>
      <bias-reg>0.01</bias-reg>
      <num-factors>20</num-factors>
      <early-stop>true</early-stop>
    </alg>
    <!-- METRICS SECTION -->
    <metric>
      <ranking>false</ranking>
      <!-- <list-size>10</list-size> -->
      <class>rmse</class>
    </metric>
    <!-- POST-PROCESSING SECTION -->
    <post>
      <script lang="python3" src="system">
        <script-name>results_to_csv.py</script-name>
        <param name="option">all</param>
      </script>
      <script lang="python3" src="system">
        <script-name>result_graphics.py</script-name>
        <param name="browser">true</param>
      </script>
      <script lang="python3" src="system">
        <script-name>slack_post.py</script-name>
        <param name="option">message</param>
        <param name="channel">la_bot</param>
        <param name="encrypted_key">../keys/slack-api.enc</param>
        <param name="message">Experiment complete</param>
        <param name="password"/>
      </script>
      <script lang="python3" src="system">
        <script-name>slack_post.py</script-name>
        <param name="option">file</param>
        <param name="channel">la_bot</param>
        <param name="encrypted_key">../keys/slack-api.enc</param>
        <param name="file">post/viz-bar-NormalizedDCG.jpg</param>
        <param name="message">NDCG for the experiment</param>
        <param name="password"/>
      </script>
    </post>
  </config>
</study>
